fastlogistic/__init__.py
fastlogistic/logistic_cpu.py
fastlogistic/logistic_gpu.py
fastlogistic-0.1.dist-info/LICENSE
fastlogistic-0.1.dist-info/METADATA
fastlogistic-0.1.dist-info/WHEEL
fastlogistic-0.1.dist-info/top_level.txt
fastlogistic-0.1.dist-info/RECORD
